bluer_objects/__init__.py
bluer_objects/__main__.py
bluer_objects/config.env
bluer_objects/env.py
bluer_objects/markdown.py
bluer_objects/objects.py
bluer_objects/path.py
bluer_objects/sample.env
bluer_objects/urls.py
bluer_objects/.abcli/abcli.sh
bluer_objects/.abcli/actions.sh
bluer_objects/.abcli/aka.sh
bluer_objects/.abcli/alias.sh
bluer_objects/.abcli/assets.sh
bluer_objects/.abcli/bluer_objects.sh
bluer_objects/.abcli/clone.sh
bluer_objects/.abcli/create_test_asset.sh
bluer_objects/.abcli/download.sh
bluer_objects/.abcli/file.sh
bluer_objects/.abcli/gif.sh
bluer_objects/.abcli/host.sh
bluer_objects/.abcli/ls.sh
bluer_objects/.abcli/metadata.sh
bluer_objects/.abcli/mlflow.sh
bluer_objects/.abcli/object.sh
bluer_objects/.abcli/pdf.sh
bluer_objects/.abcli/select.sh
bluer_objects/.abcli/storage.sh
bluer_objects/.abcli/upload.sh
bluer_objects/.abcli/url.sh
bluer_objects/.abcli/assets/cd.sh
bluer_objects/.abcli/assets/mv.sh
bluer_objects/.abcli/assets/publish.sh
bluer_objects/.abcli/metadata/download.sh
bluer_objects/.abcli/metadata/edit.sh
bluer_objects/.abcli/metadata/get.sh
bluer_objects/.abcli/metadata/post.sh
bluer_objects/.abcli/metadata/upload.sh
bluer_objects/.abcli/mlflow/browse.sh
bluer_objects/.abcli/mlflow/cache.sh
bluer_objects/.abcli/mlflow/deploy.sh
bluer_objects/.abcli/mlflow/list_registered_models.sh
bluer_objects/.abcli/mlflow/lock.sh
bluer_objects/.abcli/mlflow/log_artifacts.sh
bluer_objects/.abcli/mlflow/log_run.sh
bluer_objects/.abcli/mlflow/run.sh
bluer_objects/.abcli/mlflow/tags.sh
bluer_objects/.abcli/mlflow/test.sh
bluer_objects/.abcli/mlflow/transition.sh
bluer_objects/.abcli/mlflow/lock/lock.sh
bluer_objects/.abcli/mlflow/lock/unlock.sh
bluer_objects/.abcli/mlflow/tags/clone.sh
bluer_objects/.abcli/mlflow/tags/get.sh
bluer_objects/.abcli/mlflow/tags/search.sh
bluer_objects/.abcli/mlflow/tags/set.sh
bluer_objects/.abcli/pdf/convert.sh
bluer_objects/.abcli/storage/clear.sh
bluer_objects/.abcli/storage/status.sh
bluer_objects-6.422.1.dist-info/licenses/LICENSE
bluer_objects-6.422.1.dist-info/METADATA
bluer_objects-6.422.1.dist-info/WHEEL
bluer_objects-6.422.1.dist-info/top_level.txt
bluer_objects-6.422.1.dist-info/RECORD
