Metadata-Version: 2.4
Name: bluer_objects
Version: 6.422.1
Summary: 🌀 Object management in Bash.
Home-page: https://github.com/kamangir/bluer-objects
Author: Arash Abadpour (Kamangir)
Author-email: arash.abadpour@gmail.com
License: CC0-1.0
Classifier: Programming Language :: Python :: 3
Classifier: Programming Language :: Unix Shell
Classifier: Operating System :: OS Independent
License-File: LICENSE
Requires-Dist: bluer_ai
Requires-Dist: boto3
Requires-Dist: webdavclient3
Requires-Dist: dill
Requires-Dist: mlflow
Requires-Dist: pandas
Requires-Dist: urllib3
Provides-Extra: opencv
Requires-Dist: opencv-python; extra == "opencv"
Dynamic: author
Dynamic: author-email
Dynamic: classifier
Dynamic: description
Dynamic: description-content-type
Dynamic: home-page
Dynamic: license
Dynamic: license-file
Dynamic: provides-extra
Dynamic: requires-dist
Dynamic: summary
